setup.py
json_tools.egg-info/PKG-INFO
json_tools.egg-info/SOURCES.txt
json_tools.egg-info/dependency_links.txt
json_tools.egg-info/entry_points.txt
json_tools.egg-info/requires.txt
json_tools.egg-info/top_level.txt
lib/__init__.py
lib/__main__.py
lib/diff.py
lib/loader.py
lib/patch.py
lib/path.py
lib/print_style.py
lib/printer.py