Metadata-Version: 1.1
Name: json_tools
Version: 0.4.1
Summary: A set of tools to manipulate JSON: diff, patch, pretty-printing
Home-page: https://bitbucket.org/vadim_semenov/json_tools
Author: Vadim Semenov
Author-email: protoss.player@gmail.com
License: UNKNOWN
Keywords: json
Platform: UNKNOWN
Classifier: Development Status :: 4 - Beta
Classifier: Environment :: Console
Classifier: Intended Audience :: Developers
Classifier: Intended Audience :: System Administrators
Classifier: Operating System :: Unix
Classifier: Programming Language :: Python
Classifier: Programming Language :: Python :: 2.6
Classifier: Topic :: Software Development
Classifier: Topic :: Software Development :: Libraries
Classifier: Topic :: Software Development :: Libraries :: Python Modules
Classifier: Topic :: Utilities
Classifier: License :: OSI Approved :: MIT License
